kms_dl_module/__init__.py
kms_dl_module/classification.py
kms_dl_module/regression.py
kms_dl_module/text_classification.py
kms_dl_module-0.1.0.dist-info/LICENSE
kms_dl_module-0.1.0.dist-info/METADATA
kms_dl_module-0.1.0.dist-info/WHEEL
kms_dl_module-0.1.0.dist-info/top_level.txt
kms_dl_module-0.1.0.dist-info/RECORD
