Metadata-Version: 2.1
Name: kms-dl-module
Version: 0.1.0
Summary: A package for deep learning models including time series forecasting, classification, and text classification
Home-page: UNKNOWN
Author: KMS
Author-email: kms994438@gmail.com
License: UNKNOWN
Platform: UNKNOWN
Classifier: Programming Language :: Python :: 3
Classifier: License :: OSI Approved :: MIT License
Classifier: Operating System :: OS Independent
Requires-Python: >=3.3
License-File: LICENSE
Requires-Dist: keras
Requires-Dist: matplotlib
Requires-Dist: nltk
Requires-Dist: numpy
Requires-Dist: pandas
Requires-Dist: scikit-learn
Requires-Dist: seaborn
Requires-Dist: setuptools
Requires-Dist: tensorflow
Requires-Dist: tensorflow-intel
